README.txt
TODO.txt
bootstrap.py
buildout.cfg
setup.py
bootstrap/bootstrap.py
src/zc/__init__.py
src/zc.testbrowser.egg-info/PKG-INFO
src/zc.testbrowser.egg-info/SOURCES.txt
src/zc.testbrowser.egg-info/dependency_links.txt
src/zc.testbrowser.egg-info/namespace_packages.txt
src/zc.testbrowser.egg-info/not-zip-safe
src/zc.testbrowser.egg-info/requires.txt
src/zc.testbrowser.egg-info/top_level.txt
src/zc/testbrowser/README.txt
src/zc/testbrowser/__init__.py
src/zc/testbrowser/browser.py
src/zc/testbrowser/dummymodules.py
src/zc/testbrowser/headers.txt
src/zc/testbrowser/interfaces.py
src/zc/testbrowser/real.js
src/zc/testbrowser/real.py
src/zc/testbrowser/screen-shots.txt
src/zc/testbrowser/tests.py
src/zc/testbrowser/ftests/__init__.py
src/zc/testbrowser/ftests/controls.html
src/zc/testbrowser/ftests/forms.html
src/zc/testbrowser/ftests/ftesting.zcml
src/zc/testbrowser/ftests/index.html
src/zc/testbrowser/ftests/navigate.html
src/zc/testbrowser/ftests/notitle.html
src/zc/testbrowser/ftests/oneform.html
src/zc/testbrowser/ftests/target.html
src/zc/testbrowser/ftests/test.css
src/zc/testbrowser/ftests/test.txt
src/zc/testbrowser/ftests/zope3logo.gif
