Metadata-Version: 1.0
Name: zc.testbrowser
Version: 1.0a2
Summary: Programmable web browser for functional black-box testing of web applications
Home-page: http://pypi.python.org/pypi/zc.testbrowser
Author: Zope Corporation and Contributors
Author-email: zope3-dev@zope.org
License: ZPL 2.1
Platform: UNKNOWN
Classifier: Environment :: Web Environment
Classifier: Intended Audience :: Developers
Classifier: License :: OSI Approved :: Zope Public License
Classifier: Programming Language :: Python
Classifier: Topic :: Software Development :: Testing
Classifier: Topic :: Internet :: WWW/HTTP
